arepoICgen/__init__.py
arepoICgen/arepoOut.py
arepoICgen/bonnorEbertSphere.py
arepoICgen/boxCreation.py
arepoICgen/densityPerturbations.py
arepoICgen/generateICs.py
arepoICgen/lowDensityPadding.py
arepoICgen/massAndEnergy.py
arepoICgen/rotation.py
arepoICgen/shapeTypes.py
arepoICgen/turbulence.py
arepoicgen-0.1.14.dist-info/METADATA
arepoicgen-0.1.14.dist-info/WHEEL
arepoicgen-0.1.14.dist-info/top_level.txt
arepoicgen-0.1.14.dist-info/RECORD
