Metadata-Version: 2.2
Name: arepoICgen
Version: 0.1.14
Summary: Package for generating initial conditions for AREPO
Home-page: https://github.com/clonematthew/arepoICgen
Author: Matt Cusack
Author-email: cusackmt@cardiff.ac.uk
Dynamic: author
Dynamic: author-email
Dynamic: description
Dynamic: description-content-type
Dynamic: home-page
Dynamic: summary
